django_grep_db-1.1.2.dist-info/DESCRIPTION.rst
django_grep_db-1.1.2.dist-info/METADATA
django_grep_db-1.1.2.dist-info/RECORD
django_grep_db-1.1.2.dist-info/WHEEL
django_grep_db-1.1.2.dist-info/metadata.json
django_grep_db-1.1.2.dist-info/top_level.txt
django_grepdb/__init__.py
django_grepdb/version.py
django_grepdb/management/__init__.py
django_grepdb/management/commands/__init__.py
django_grepdb/management/commands/grepdb.py
django_grepdb/tests/__init__.py
django_grepdb/tests/admin_urls.py
django_grepdb/tests/models.py
django_grepdb/tests/test_admin_links.py
django_grepdb/tests/test_basics.py
django_grepdb/tests/test_field_types.py
django_grepdb/tests/test_presets.py
django_grepdb/tests/test_show_values.py
django_grepdb/tests/urls.py
django_grepdb/tests/migrations/0001_initial.py
django_grepdb/tests/migrations/__init__.py
