Metadata-Version: 2.0
Name: django-grep-db
Version: 1.1.2
Summary: A simple Django app for command-line searching via the ORM
Home-page: https://github.com/exonian/django-grep-db
Author: Michael Blatherwick
Author-email: michael.blatherwick@exeter.oxon.org
License: MIT
Keywords: django search grep cli
Platform: UNKNOWN
Requires-Dist: colorama (>=0.3.3)
Requires-Dist: django (>=1.8)
Requires-Dist: termcolor (>=1.1.0)
